scripts/generate_shorts.py
shorts_generator/__init__.py
shorts_generator/configs/__init__.py
shorts_generator/configs/actor.py
shorts_generator/configs/voice.py
shorts_generator/generator.py
shorts_generator/generators/__init__.py
shorts_generator/generators/audio.py
shorts_generator/generators/image.py
shorts_generator/generators/script.py
shorts_generator/generators/video.py
shorts_generator/workspace.py
shorts_generator-0.1.3.dist-info/LICENSE
shorts_generator-0.1.3.dist-info/METADATA
shorts_generator-0.1.3.dist-info/WHEEL
shorts_generator-0.1.3.dist-info/entry_points.txt
shorts_generator-0.1.3.dist-info/RECORD
