Metadata-Version: 2.1
Name: shorts-generator
Version: 0.1.3
Summary: 
Home-page: https://github.com/JingunSnack/ShortsGenerator
License: MIT
Author: Jingun Hong
Author-email: jingun.hong@gmail.com
Requires-Python: >=3.11,<4.0
Classifier: License :: OSI Approved :: MIT License
Classifier: Programming Language :: Python :: 3
Classifier: Programming Language :: Python :: 3.11
Classifier: Programming Language :: Python :: 3.12
Requires-Dist: argparse (>=1.4.0,<2.0.0)
Requires-Dist: moviepy (>=1.0.3,<2.0.0)
Requires-Dist: openai (>=1.25.1,<2.0.0)
Requires-Dist: pillow (==9.5.0)
Requires-Dist: pyyaml (>=6.0.1,<7.0.0)
Requires-Dist: requests (>=2.31.0,<3.0.0)
Project-URL: Repository, https://github.com/JingunSnack/ShortsGenerator
